odoo/addons/website_contact_extend/README.rst
odoo/addons/website_contact_extend/__init__.py
odoo/addons/website_contact_extend/__manifest__.py
odoo/addons/website_contact_extend/controllers/__init__.py
odoo/addons/website_contact_extend/controllers/myfilter.py
odoo/addons/website_contact_extend/data/email_templates.xml
odoo/addons/website_contact_extend/i18n/de.po
odoo/addons/website_contact_extend/i18n/en_US.po
odoo/addons/website_contact_extend/i18n/fr.po
odoo/addons/website_contact_extend/i18n/it.po
odoo/addons/website_contact_extend/i18n/website_contact_extend.pot
odoo/addons/website_contact_extend/models/__init__.py
odoo/addons/website_contact_extend/models/res_partner.py
odoo/addons/website_contact_extend/readme/CONFIGURE.rst
odoo/addons/website_contact_extend/readme/DESCRIPTION.rst
odoo/addons/website_contact_extend/readme/USAGE.rst
odoo/addons/website_contact_extend/static/description/icon.png
odoo/addons/website_contact_extend/static/description/index.html
odoo/addons/website_contact_extend/views/contact_report.xml
odoo/addons/website_contact_extend/views/res_partner.xml
odoo/addons/website_contact_extend/views/website_contact.xml
odoo11_addon_website_contact_extend-11.0.1.0.0.99.dev10.dist-info/METADATA
odoo11_addon_website_contact_extend-11.0.1.0.0.99.dev10.dist-info/WHEEL
odoo11_addon_website_contact_extend-11.0.1.0.0.99.dev10.dist-info/top_level.txt
odoo11_addon_website_contact_extend-11.0.1.0.0.99.dev10.dist-info/RECORD
